summarizedexperiment/RangedSummarizedExperiment.py
summarizedexperiment/SummarizedExperiment.py
summarizedexperiment/__init__.py
summarizedexperiment/_combineutils.py
summarizedexperiment/_frameutils.py
summarizedexperiment/base.py
summarizedexperiment/type_checks.py
summarizedexperiment-0.6.5.dist-info/licenses/LICENSE.txt
summarizedexperiment-0.6.5.dist-info/METADATA
summarizedexperiment-0.6.5.dist-info/WHEEL
summarizedexperiment-0.6.5.dist-info/top_level.txt
summarizedexperiment-0.6.5.dist-info/RECORD
