Metadata-Version: 2.4
Name: SummarizedExperiment
Version: 0.6.5
Summary: Container to represent data from genomic experiments
Home-page: https://github.com/BiocPy/summarizedexperiment
Author: jkanche
Author-email: jayaram.kancherla@gmail.com
License: MIT
Project-URL: Documentation, https://github.com/BiocPy/summarizedexperiment
Platform: any
Classifier: Development Status :: 4 - Beta
Classifier: Programming Language :: Python
Requires-Python: >=3.9
License-File: LICENSE.txt
Requires-Dist: importlib-metadata; python_version < "3.8"
Requires-Dist: genomicranges>=0.8.2
Requires-Dist: biocframe>=0.7.2
Requires-Dist: biocutils>=0.3.3
Provides-Extra: optional
Requires-Dist: anndata; extra == "optional"
Requires-Dist: scipy; extra == "optional"
Requires-Dist: delayedarray; extra == "optional"
Provides-Extra: testing
Requires-Dist: setuptools; extra == "testing"
Requires-Dist: pytest; extra == "testing"
Requires-Dist: pytest-cov; extra == "testing"
Requires-Dist: anndata; extra == "testing"
Requires-Dist: delayedarray; extra == "testing"
Dynamic: license-file
